{
  "moments": [
    {
      "year": "2025",
      "date": "2025年12月21日 12:04",
      "text": "第一口knd先吃",
      "imgs": [
        "images/photo9.jpg"
      ]
    },
    {
      "year": "2025",
      "date": "2025年12月19日 23:37",
      "text": "忙活差不多一天在博客上？好像上午是弄自动读取手机app，下午开始弄博客来着，不过总之确实有成效！MacroDroid这个自动化感觉比Tasker靠谱，界面也比tasker好看。然后我也终于成功简单地美化了一下博客www\n\n新背景真好看呀",
      "imgs": [
        "images/photo3.jpg",
        "images/photo4.jpg",
        "images/photo5.jpg",
        "images/photo6.jpg"
      ]
    },
    {
      "year": "2025",
      "date": "2025年12月21日",
      "text": "分享一段最近拍的视频 🎬",
      "video": "videos/video1.mp4"
    },
    {
      "year": "2025",
      "date": "2025年12月20日",
      "text": "今日歌单推荐 🎧",
      "music": {
        "title": "アポフェニア（妄想症）",
        "artist": "黒うさぎ",
        "url": "https://music.163.com/song?id=2758918682",
        "cover": "http://p1.music.126.net/FppBXTTqz4QFkHo7DLE3TA==/109951172194520509.jpg"
      }
    },
    {
      "year": "2025",
      "date": "2025年11月26日 11:30",
      "text": "我不想让色情网站侮辱我的域名（悲）",
      "imgs": [
        "images/photo7.jpg",
        "images/photo8.jpg"
      ]
    },
    {
      "year": "2025",
      "date": "2025年01月29日 11:59",
      "text": "新年快乐喵🧧",
      "imgs": [
        "images/photo11.jpg",
        "images/photo10.jpg"
      ]
    },
    {
      "year": "2025",
      "date": "2025年01月25日 18:45",
      "text": "电脑和音箱快点到吧求你了，没有你我不行……\n顺便说最近玩那个幻想鱼箱，我真觉得开着这个游戏，然后用音箱在房间里外放，待在这个房间里就感觉生活像游戏一样自带bgm，我就像是一个游戏角色一样。很特别的感觉。",
      "imgs": [
        "images/photo12.jpg"
      ]
    },
    {
      "year": "2025",
      "date": "2025年01月16日 22:30",
      "text": "给平板换了电视风格的桌面，感觉很酷",
      "imgs": [
        "images/photo13.jpg",
        "images/photo14.jpg"
      ]
    },
    {
      "year": "2025",
      "date": "2025年01月10日 13:55",
      "text": "花了三个小时（存档共计）终于把歌姬计划extend的曲子开完了\n太喜欢∞这身服装了",
      "imgs": [
        "images/photo15.jpg",
        "images/photo16.jpg"
      ]
    }
  ]
}
